innatis/__init__.py
innatis/test.py
innatis/classifiers/__init__.py
innatis/classifiers/bert_intent_classifier.py
innatis/classifiers/bert/__init__.py
innatis/classifiers/bert/optimization.py
innatis/classifiers/bert/run_classifier.py
innatis/classifiers/bert/tokenization.py
innatis/extractors/__init__.py
innatis/extractors/composite_data_extractor.py
innatis/extractors/composite_entity_extractor.py
innatis/extractors/entity_synonyms.py
innatis/featurizers/__init__.py
innatis/featurizers/universal_sentence_encoder_featurizer.py
innatis-0.5.8.dist-info/DESCRIPTION.rst
innatis-0.5.8.dist-info/METADATA
innatis-0.5.8.dist-info/RECORD
innatis-0.5.8.dist-info/WHEEL
innatis-0.5.8.dist-info/metadata.json
innatis-0.5.8.dist-info/top_level.txt
